{
  "Listings": 
    {
      "Language": "en",
      "Description": "Looking for a powerful cybersecurity solution for your devices? Features essential security, online privacy, and personal information awareness",
      "WhatsNew": "Protects against personal information leaks",
      "ProductFeatures": ["Autmatic scan", "online privacy"],
      "ShortDescription": "Features essential security for ms office",
      "SearchTerms": [
        "CyberProtectHomeOffice",
        "Acronis",
        "cyber protect"
      ],
      "AdditionalLicenseTerms": "Proprietary",
      "Copyright": "Microsoft 2025",
      "DevelopedBy": "Test User",
      "Requirements": [
        {
          "MinimumRequirement": null,
          "RecommendedRequirement": null,
          "HardwareItemType": null
        }
      ],
      "ContactInfo": "testUser@outlook.com"
    }
}
